{".class": "MypyFile", "_fullname": "qcodes.dataset.sqlite.connection", "is_partial_stub_package": false, "is_stub": false, "names": {".class": "SymbolTable", "Any": {".class": "SymbolTableNode", "cross_ref": "typing.Any", "kind": "Gdef"}, "ConnectionPlus": {".class": "SymbolTableNode", "kind": "Gdef", "node": {".class": "TypeInfo", "_promote": null, "abstract_attributes": [], "bases": ["builtins.object"], "declared_metaclass": null, "defn": {".class": "ClassDef", "fullname": "qcodes.dataset.sqlite.connection.ConnectionPlus", "name": "ConnectionPlus", "type_vars": []}, "flags": ["fallback_to_any"], "fullname": "qcodes.dataset.sqlite.connection.ConnectionPlus", "metaclass_type": null, "metadata": {}, "module_name": "qcodes.dataset.sqlite.connection", "mro": ["qcodes.dataset.sqlite.connection.ConnectionPlus", "builtins.object"], "names": {".class": "SymbolTable", "__init__": {".class": "SymbolTableNode", "kind": "Mdef", "node": {".class": "FuncDef", "arg_kinds": [0, 0], "arg_names": ["self", "sqlite3_connection"], "flags": [], "fullname": "qcodes.dataset.sqlite.connection.ConnectionPlus.__init__", "name": "__init__", "type": {".class": "CallableType", "arg_kinds": [0, 0], "arg_names": ["self", "sqlite3_connection"], "arg_types": ["qcodes.dataset.sqlite.connection.ConnectionPlus", "sqlite3.dbapi2.Connection"], "bound_args": [], "def_extras": {"first_arg": "self"}, "fallback": "builtins.function", "implicit": false, "is_ellipsis_args": false, "name": "__init__ of ConnectionPlus", "ret_type": {".class": "NoneTyp"}, "variables": []}}}, "atomic_in_progress": {".class": "SymbolTableNode", "kind": "Mdef", "node": {".class": "Var", "flags": ["is_initialized_in_class"], "fullname": "qcodes.dataset.sqlite.connection.ConnectionPlus.atomic_in_progress", "name": "atomic_in_progress", "type": "builtins.bool"}}}, "tuple_type": null, "type_vars": [], "typeddict_type": null}}, "Union": {".class": "SymbolTableNode", "cross_ref": "typing.Union", "kind": "Gdef"}, "__doc__": {".class": "SymbolTableNode", "kind": "Gdef", "node": {".class": "Var", "flags": [], "fullname": "qcodes.dataset.sqlite.connection.__doc__", "name": "__doc__", "type": "builtins.str"}}, "__file__": {".class": "SymbolTableNode", "kind": "Gdef", "node": {".class": "Var", "flags": [], "fullname": "qcodes.dataset.sqlite.connection.__file__", "name": "__file__", "type": "builtins.str"}}, "__name__": {".class": "SymbolTableNode", "kind": "Gdef", "node": {".class": "Var", "flags": [], "fullname": "qcodes.dataset.sqlite.connection.__name__", "name": "__name__", "type": "builtins.str"}}, "__package__": {".class": "SymbolTableNode", "kind": "Gdef", "node": {".class": "Var", "flags": [], "fullname": "qcodes.dataset.sqlite.connection.__package__", "name": "__package__", "type": "builtins.str"}}, "atomic": {".class": "SymbolTableNode", "kind": "Gdef", "node": {".class": "Decorator", "func": {".class": "FuncDef", "arg_kinds": [0], "arg_names": ["conn"], "flags": ["is_generator", "is_decorated"], "fullname": "qcodes.dataset.sqlite.connection.atomic", "name": "atomic", "type": {".class": "CallableType", "arg_kinds": [0], "arg_names": ["conn"], "arg_types": ["qcodes.dataset.sqlite.connection.ConnectionPlus"], "bound_args": [], "def_extras": {"first_arg": null}, "fallback": "builtins.function", "implicit": false, "is_ellipsis_args": false, "name": "atomic", "ret_type": {".class": "AnyType", "missing_import_name": null, "source_any": null, "type_of_any": 1}, "variables": []}}, "is_overload": false, "var": {".class": "Var", "flags": [], "fullname": "qcodes.dataset.sqlite.connection.atomic", "name": "atomic", "type": {".class": "CallableType", "arg_kinds": [0], "arg_names": ["conn"], "arg_types": ["qcodes.dataset.sqlite.connection.ConnectionPlus"], "bound_args": [], "def_extras": {}, "fallback": "builtins.function", "implicit": false, "is_ellipsis_args": false, "name": "atomic", "ret_type": {".class": "Instance", "args": [{".class": "AnyType", "missing_import_name": null, "source_any": {".class": "AnyType", "missing_import_name": null, "source_any": null, "type_of_any": 1}, "type_of_any": 7}], "type_ref": "contextlib.GeneratorContextManager"}, "variables": []}}}}, "atomic_transaction": {".class": "SymbolTableNode", "kind": "Gdef", "node": {".class": "FuncDef", "arg_kinds": [0, 0, 2], "arg_names": ["conn", "sql", "args"], "flags": [], "fullname": "qcodes.dataset.sqlite.connection.atomic_transaction", "name": "atomic_transaction", "type": {".class": "CallableType", "arg_kinds": [0, 0, 2], "arg_names": ["conn", "sql", "args"], "arg_types": ["qcodes.dataset.sqlite.connection.ConnectionPlus", "builtins.str", {".class": "AnyType", "missing_import_name": null, "source_any": null, "type_of_any": 2}], "bound_args": [], "def_extras": {"first_arg": null}, "fallback": "builtins.function", "implicit": false, "is_ellipsis_args": false, "name": "atomic_transaction", "ret_type": "sqlite3.dbapi2.Cursor", "variables": []}}}, "contextmanager": {".class": "SymbolTableNode", "cross_ref": "contextlib.contextmanager", "kind": "Gdef"}, "log": {".class": "SymbolTableNode", "kind": "Gdef", "node": {".class": "Var", "flags": [], "fullname": "qcodes.dataset.sqlite.connection.log", "name": "log", "type": "logging.Logger"}}, "logging": {".class": "SymbolTableNode", "cross_ref": "logging", "kind": "Gdef"}, "make_connection_plus_from": {".class": "SymbolTableNode", "kind": "Gdef", "node": {".class": "FuncDef", "arg_kinds": [0], "arg_names": ["conn"], "flags": [], "fullname": "qcodes.dataset.sqlite.connection.make_connection_plus_from", "name": "make_connection_plus_from", "type": {".class": "CallableType", "arg_kinds": [0], "arg_names": ["conn"], "arg_types": [{".class": "UnionType", "items": ["sqlite3.dbapi2.Connection", "qcodes.dataset.sqlite.connection.ConnectionPlus"]}], "bound_args": [], "def_extras": {"first_arg": null}, "fallback": "builtins.function", "implicit": false, "is_ellipsis_args": false, "name": "make_connection_plus_from", "ret_type": "qcodes.dataset.sqlite.connection.ConnectionPlus", "variables": []}}}, "sqlite3": {".class": "SymbolTableNode", "cross_ref": "sqlite3", "kind": "Gdef"}, "transaction": {".class": "SymbolTableNode", "kind": "Gdef", "node": {".class": "FuncDef", "arg_kinds": [0, 0, 2], "arg_names": ["conn", "sql", "args"], "flags": [], "fullname": "qcodes.dataset.sqlite.connection.transaction", "name": "transaction", "type": {".class": "CallableType", "arg_kinds": [0, 0, 2], "arg_names": ["conn", "sql", "args"], "arg_types": ["qcodes.dataset.sqlite.connection.ConnectionPlus", "builtins.str", {".class": "AnyType", "missing_import_name": null, "source_any": null, "type_of_any": 2}], "bound_args": [], "def_extras": {"first_arg": null}, "fallback": "builtins.function", "implicit": false, "is_ellipsis_args": false, "name": "transaction", "ret_type": "sqlite3.dbapi2.Cursor", "variables": []}}}, "wrapt": {".class": "SymbolTableNode", "kind": "Gdef", "node": {".class": "Var", "flags": ["is_suppressed_import"], "fullname": "qcodes.dataset.sqlite.connection.wrapt", "name": "wrapt", "type": {".class": "AnyType", "missing_import_name": "qcodes.dataset.sqlite.connection.wrapt", "source_any": null, "type_of_any": 3}}}}, "path": "qcodes/dataset/sqlite/connection.py"}