{".class": "MypyFile", "_fullname": "qcodes.instrument_drivers.Keysight.private.error_handling", "is_partial_stub_package": false, "is_stub": false, "names": {".class": "SymbolTable", "AbstractInstrument": {".class": "SymbolTableNode", "cross_ref": "qcodes.instrument.base.AbstractInstrument", "kind": "Gdef"}, "KeysightErrorQueueMixin": {".class": "SymbolTableNode", "kind": "Gdef", "node": {".class": "TypeInfo", "_promote": null, "abstract_attributes": [], "bases": ["qcodes.instrument.base.AbstractInstrument"], "declared_metaclass": null, "defn": {".class": "ClassDef", "fullname": "qcodes.instrument_drivers.Keysight.private.error_handling.KeysightErrorQueueMixin", "name": "KeysightErrorQueueMixin", "type_vars": []}, "flags": [], "fullname": "qcodes.instrument_drivers.Keysight.private.error_handling.KeysightErrorQueueMixin", "metaclass_type": "abc.ABCMeta", "metadata": {}, "module_name": "qcodes.instrument_drivers.Keysight.private.error_handling", "mro": ["qcodes.instrument_drivers.Keysight.private.error_handling.KeysightErrorQueueMixin", "qcodes.instrument.base.AbstractInstrument", "abc.ABC", "builtins.object"], "names": {".class": "SymbolTable", "error": {".class": "SymbolTableNode", "kind": "Mdef", "node": {".class": "FuncDef", "arg_kinds": [0], "arg_names": ["self"], "flags": [], "fullname": "qcodes.instrument_drivers.Keysight.private.error_handling.KeysightErrorQueueMixin.error", "name": "error", "type": {".class": "CallableType", "arg_kinds": [0], "arg_names": ["self"], "arg_types": ["qcodes.instrument_drivers.Keysight.private.error_handling.KeysightErrorQueueMixin"], "bound_args": [], "def_extras": {"first_arg": "self"}, "fallback": "builtins.function", "implicit": false, "is_ellipsis_args": false, "name": "error of KeysightErrorQueueMixin", "ret_type": {".class": "TupleType", "fallback": {".class": "Instance", "args": [{".class": "AnyType", "missing_import_name": null, "source_any": null, "type_of_any": 6}], "type_ref": "builtins.tuple"}, "implicit": false, "items": ["builtins.int", "builtins.str"]}, "variables": []}}}, "flush_error_queue": {".class": "SymbolTableNode", "kind": "Mdef", "node": {".class": "FuncDef", "arg_kinds": [0, 1], "arg_names": ["self", "verbose"], "flags": [], "fullname": "qcodes.instrument_drivers.Keysight.private.error_handling.KeysightErrorQueueMixin.flush_error_queue", "name": "flush_error_queue", "type": {".class": "CallableType", "arg_kinds": [0, 1], "arg_names": ["self", "verbose"], "arg_types": ["qcodes.instrument_drivers.Keysight.private.error_handling.KeysightErrorQueueMixin", "builtins.bool"], "bound_args": [], "def_extras": {"first_arg": "self"}, "fallback": "builtins.function", "implicit": false, "is_ellipsis_args": false, "name": "flush_error_queue of KeysightErrorQueueMixin", "ret_type": {".class": "NoneTyp"}, "variables": []}}}}, "tuple_type": null, "type_vars": [], "typeddict_type": null}}, "Tuple": {".class": "SymbolTableNode", "cross_ref": "typing.Tuple", "kind": "Gdef"}, "__doc__": {".class": "SymbolTableNode", "kind": "Gdef", "node": {".class": "Var", "flags": [], "fullname": "qcodes.instrument_drivers.Keysight.private.error_handling.__doc__", "name": "__doc__", "type": "builtins.str"}}, "__file__": {".class": "SymbolTableNode", "kind": "Gdef", "node": {".class": "Var", "flags": [], "fullname": "qcodes.instrument_drivers.Keysight.private.error_handling.__file__", "name": "__file__", "type": "builtins.str"}}, "__name__": {".class": "SymbolTableNode", "kind": "Gdef", "node": {".class": "Var", "flags": [], "fullname": "qcodes.instrument_drivers.Keysight.private.error_handling.__name__", "name": "__name__", "type": "builtins.str"}}, "__package__": {".class": "SymbolTableNode", "kind": "Gdef", "node": {".class": "Var", "flags": [], "fullname": "qcodes.instrument_drivers.Keysight.private.error_handling.__package__", "name": "__package__", "type": "builtins.str"}}}, "path": "qcodes/instrument_drivers/Keysight/private/error_handling.py"}
