{".class": "MypyFile", "_fullname": "qcodes.data.hdf5_format_hickle", "is_partial_stub_package": false, "is_stub": false, "names": {".class": "SymbolTable", "HDF5Format": {".class": "SymbolTableNode", "cross_ref": "qcodes.data.hdf5_format.HDF5Format", "kind": "Gdef"}, "HDF5FormatHickle": {".class": "SymbolTableNode", "kind": "Gdef", "node": {".class": "TypeInfo", "_promote": null, "abstract_attributes": [], "bases": ["qcodes.data.hdf5_format.HDF5Format"], "declared_metaclass": null, "defn": {".class": "ClassDef", "fullname": "qcodes.data.hdf5_format_hickle.HDF5FormatHickle", "name": "HDF5FormatHickle", "type_vars": []}, "flags": [], "fullname": "qcodes.data.hdf5_format_hickle.HDF5FormatHickle", "metaclass_type": null, "metadata": {}, "module_name": "qcodes.data.hdf5_format_hickle", "mro": ["qcodes.data.hdf5_format_hickle.HDF5FormatHickle", "qcodes.data.hdf5_format.HDF5Format", "qcodes.data.format.Formatter", "builtins.object"], "names": {".class": "SymbolTable", "_format_tag": {".class": "SymbolTableNode", "kind": "Mdef", "node": {".class": "Var", "flags": ["is_initialized_in_class"], "fullname": "qcodes.data.hdf5_format_hickle.HDF5FormatHickle._format_tag", "name": "_format_tag", "type": "builtins.str"}}, "_metadata_file": {".class": "SymbolTableNode", "kind": "Mdef", "node": {".class": "Var", "flags": ["is_initialized_in_class"], "fullname": "qcodes.data.hdf5_format_hickle.HDF5FormatHickle._metadata_file", "name": "_metadata_file", "type": "builtins.str"}}, "read_metadata": {".class": "SymbolTableNode", "kind": "Mdef", "node": {".class": "FuncDef", "arg_kinds": [0, 0], "arg_names": ["self", "data_set"], "flags": [], "fullname": "qcodes.data.hdf5_format_hickle.HDF5FormatHickle.read_metadata", "name": "read_metadata", "type": null}}, "write_metadata": {".class": "SymbolTableNode", "kind": "Mdef", "node": {".class": "FuncDef", "arg_kinds": [0, 0, 1, 1, 1], "arg_names": ["self", "data_set", "io_manager", "location", "read_first"], "flags": [], "fullname": "qcodes.data.hdf5_format_hickle.HDF5FormatHickle.write_metadata", "name": "write_metadata", "type": null}}}, "tuple_type": null, "type_vars": [], "typeddict_type": null}}, "__doc__": {".class": "SymbolTableNode", "kind": "Gdef", "node": {".class": "Var", "flags": [], "fullname": "qcodes.data.hdf5_format_hickle.__doc__", "name": "__doc__", "type": "builtins.str"}}, "__file__": {".class": "SymbolTableNode", "kind": "Gdef", "node": {".class": "Var", "flags": [], "fullname": "qcodes.data.hdf5_format_hickle.__file__", "name": "__file__", "type": "builtins.str"}}, "__name__": {".class": "SymbolTableNode", "kind": "Gdef", "node": {".class": "Var", "flags": [], "fullname": "qcodes.data.hdf5_format_hickle.__name__", "name": "__name__", "type": "builtins.str"}}, "__package__": {".class": "SymbolTableNode", "kind": "Gdef", "node": {".class": "Var", "flags": [], "fullname": "qcodes.data.hdf5_format_hickle.__package__", "name": "__package__", "type": "builtins.str"}}, "deep_update": {".class": "SymbolTableNode", "cross_ref": "qcodes.utils.helpers.deep_update", "kind": "Gdef"}, "hickle": {".class": "SymbolTableNode", "kind": "Gdef", "node": {".class": "Var", "flags": ["is_suppressed_import"], "fullname": "qcodes.data.hdf5_format_hickle.hickle", "name": "hickle", "type": {".class": "AnyType", "missing_import_name": "qcodes.data.hdf5_format_hickle.hickle", "source_any": null, "type_of_any": 3}}}, "log": {".class": "SymbolTableNode", "kind": "Gdef", "node": {".class": "Var", "flags": [], "fullname": "qcodes.data.hdf5_format_hickle.log", "name": "log", "type": "logging.Logger"}}, "logging": {".class": "SymbolTableNode", "cross_ref": "logging", "kind": "ModuleRef"}}, "path": "qcodes/data/hdf5_format_hickle.py"}
