{".class": "MypyFile", "_fullname": "qcodes.instrument_drivers.Keysight.N52xx", "is_partial_stub_package": false, "is_stub": false, "names": {".class": "SymbolTable", "Any": {".class": "SymbolTableNode", "cross_ref": "typing.Any", "kind": "Gdef"}, "ArrayParameter": {".class": "SymbolTableNode", "cross_ref": "qcodes.instrument.parameter.ArrayParameter", "kind": "Gdef"}, "Bool": {".class": "SymbolTableNode", "cross_ref": "qcodes.utils.validators.Bool", "kind": "Gdef"}, "ChannelList": {".class": "SymbolTableNode", "cross_ref": "qcodes.instrument.channel.ChannelList", "kind": "Gdef"}, "Enum": {".class": "SymbolTableNode", "cross_ref": "qcodes.utils.validators.Enum", "kind": "Gdef"}, "FormattedSweep": {".class": "SymbolTableNode", "kind": "Gdef", "node": {".class": "TypeInfo", "_promote": null, "abstract_attributes": [], "bases": ["qcodes.instrument_drivers.Keysight.N52xx.PNASweep"], "declared_metaclass": null, "defn": {".class": "ClassDef", "fullname": "qcodes.instrument_drivers.Keysight.N52xx.FormattedSweep", "name": "FormattedSweep", "type_vars": []}, "flags": [], "fullname": "qcodes.instrument_drivers.Keysight.N52xx.FormattedSweep", "metaclass_type": null, "metadata": {}, "module_name": "qcodes.instrument_drivers.Keysight.N52xx", "mro": ["qcodes.instrument_drivers.Keysight.N52xx.FormattedSweep", "qcodes.instrument_drivers.Keysight.N52xx.PNASweep", "qcodes.instrument.parameter.ArrayParameter", "qcodes.instrument.parameter._BaseParameter", "qcodes.utils.metadata.Metadatable", "builtins.object"], "names": {".class": "SymbolTable", "__init__": {".class": "SymbolTableNode", "kind": "Mdef", "node": {".class": "FuncDef", "arg_kinds": [0, 0, 0, 0, 0, 0, 1], "arg_names": ["self", "name", "instrument", "sweep_format", "label", "unit", "memory"], "flags": [], "fullname": "qcodes.instrument_drivers.Keysight.N52xx.FormattedSweep.__init__", "name": "__init__", "type": {".class": "CallableType", "arg_kinds": [0, 0, 0, 0, 0, 0, 1], "arg_names": ["self", "name", "instrument", "sweep_format", "label", "unit", "memory"], "arg_types": ["qcodes.instrument_drivers.Keysight.N52xx.FormattedSweep", "builtins.str", "qcodes.instrument_drivers.Keysight.N52xx.PNABase", "builtins.str", "builtins.str", "builtins.str", "builtins.bool"], "bound_args": [], "def_extras": {"first_arg": "self"}, "fallback": "builtins.function", "implicit": false, "is_ellipsis_args": false, "name": "__init__ of FormattedSweep", "ret_type": {".class": "NoneTyp"}, "variables": []}}}, "get_raw": {".class": "SymbolTableNode", "kind": "Mdef", "node": {".class": "FuncDef", "arg_kinds": [0], "arg_names": ["self"], "flags": [], "fullname": "qcodes.instrument_drivers.Keysight.N52xx.FormattedSweep.get_raw", "name": "get_raw", "type": {".class": "CallableType", "arg_kinds": [0], "arg_names": ["self"], "arg_types": ["qcodes.instrument_drivers.Keysight.N52xx.FormattedSweep"], "bound_args": [], "def_extras": {"first_arg": "self"}, "fallback": "builtins.function", "implicit": false, "is_ellipsis_args": false, "name": "get_raw of FormattedSweep", "ret_type": {".class": "Instance", "args": ["builtins.float"], "type_ref": "typing.Sequence"}, "variables": []}}}, "memory": {".class": "SymbolTableNode", "implicit": true, "kind": "Mdef", "node": {".class": "Var", "flags": [], "fullname": "qcodes.instrument_drivers.Keysight.N52xx.FormattedSweep.memory", "name": "memory", "type": "builtins.bool"}}, "sweep_format": {".class": "SymbolTableNode", "implicit": true, "kind": "Mdef", "node": {".class": "Var", "flags": [], "fullname": "qcodes.instrument_drivers.Keysight.N52xx.FormattedSweep.sweep_format", "name": "sweep_format", "type": "builtins.str"}}}, "tuple_type": null, "type_vars": [], "typeddict_type": null}}, "InstrumentChannel": {".class": "SymbolTableNode", "cross_ref": "qcodes.instrument.channel.InstrumentChannel", "kind": "Gdef"}, "Numbers": {".class": "SymbolTableNode", "cross_ref": "qcodes.utils.validators.Numbers", "kind": "Gdef"}, "PNABase": {".class": "SymbolTableNode", "kind": "Gdef", "node": {".class": "TypeInfo", "_promote": null, "abstract_attributes": [], "bases": ["qcodes.instrument.visa.VisaInstrument"], "declared_metaclass": null, "defn": {".class": "ClassDef", "fullname": "qcodes.instrument_drivers.Keysight.N52xx.PNABase", "name": "PNABase", "type_vars": []}, "flags": [], "fullname": "qcodes.instrument_drivers.Keysight.N52xx.PNABase", "metaclass_type": null, "metadata": {}, "module_name": "qcodes.instrument_drivers.Keysight.N52xx", "mro": ["qcodes.instrument_drivers.Keysight.N52xx.PNABase", "qcodes.instrument.visa.VisaInstrument", "qcodes.instrument.base.Instrument", "qcodes.instrument.base.InstrumentBase", "qcodes.utils.metadata.Metadatable", "qcodes.utils.helpers.DelegateAttributes", "builtins.object"], "names": {".class": "SymbolTable", "__init__": {".class": "SymbolTableNode", "kind": "Mdef", "node": {".class": "FuncDef", "arg_kinds": [0, 0, 0, 0, 0, 0, 0, 0, 4], "arg_names": ["self", "name", "address", "min_freq", "max_freq", "min_power", "max_power", "nports", "kwargs"], "flags": [], "fullname": "qcodes.instrument_drivers.Keysight.N52xx.PNABase.__init__", "name": "__init__", "type": {".class": "CallableType", "arg_kinds": [0, 0, 0, 0, 0, 0, 0, 0, 4], "arg_names": ["self", "name", "address", "min_freq", "max_freq", "min_power", "max_power", "nports", "kwargs"], "arg_types": ["qcodes.instrument_drivers.Keysight.N52xx.PNABase", "builtins.str", "builtins.str", {".class": "UnionType", "items": ["builtins.int", "builtins.float"]}, {".class": "UnionType", "items": ["builtins.int", "builtins.float"]}, {".class": "UnionType", "items": ["builtins.int", "builtins.float"]}, {".class": "UnionType", "items": ["builtins.int", "builtins.float"]}, "builtins.int", {".class": "AnyType", "missing_import_name": null, "source_any": null, "type_of_any": 2}], "bound_args": [], "def_extras": {"first_arg": "self"}, "fallback": "builtins.function", "implicit": false, "is_ellipsis_args": false, "name": "__init__ of PNABase", "ret_type": {".class": "NoneTyp"}, "variables": []}}}, "_set_power_limits": {".class": "SymbolTableNode", "kind": "Mdef", "node": {".class": "FuncDef", "arg_kinds": [0, 0, 0], "arg_names": ["self", "min_power", "max_power"], "flags": [], "fullname": "qcodes.instrument_drivers.Keysight.N52xx.PNABase._set_power_limits", "name": "_set_power_limits", "type": {".class": "CallableType", "arg_kinds": [0, 0, 0], "arg_names": ["self", "min_power", "max_power"], "arg_types": ["qcodes.instrument_drivers.Keysight.N52xx.PNABase", {".class": "UnionType", "items": ["builtins.int", "builtins.float"]}, {".class": "UnionType", "items": ["builtins.int", "builtins.float"]}], "bound_args": [], "def_extras": {"first_arg": "self"}, "fallback": "builtins.function", "implicit": false, "is_ellipsis_args": false, "name": "_set_power_limits of PNABase", "ret_type": {".class": "NoneTyp"}, "variables": []}}}, "_traces": {".class": "SymbolTableNode", "implicit": true, "kind": "Mdef", "node": {".class": "Var", "flags": [], "fullname": "qcodes.instrument_drivers.Keysight.N52xx.PNABase._traces", "name": "_traces", "type": "qcodes.instrument.channel.ChannelList"}}, "averages_off": {".class": "SymbolTableNode", "kind": "Mdef", "node": {".class": "FuncDef", "arg_kinds": [0], "arg_names": ["self"], "flags": [], "fullname": "qcodes.instrument_drivers.Keysight.N52xx.PNABase.averages_off", "name": "averages_off", "type": null}}, "averages_on": {".class": "SymbolTableNode", "kind": "Mdef", "node": {".class": "FuncDef", "arg_kinds": [0], "arg_names": ["self"], "flags": [], "fullname": "qcodes.instrument_drivers.Keysight.N52xx.PNABase.averages_on", "name": "averages_on", "type": null}}, "get_options": {".class": "SymbolTableNode", "kind": "Mdef", "node": {".class": "FuncDef", "arg_kinds": [0], "arg_names": ["self"], "flags": [], "fullname": "qcodes.instrument_drivers.Keysight.N52xx.PNABase.get_options", "name": "get_options", "type": {".class": "CallableType", "arg_kinds": [0], "arg_names": ["self"], "arg_types": ["qcodes.instrument_drivers.Keysight.N52xx.PNABase"], "bound_args": [], "def_extras": {"first_arg": "self"}, "fallback": "builtins.function", "implicit": false, "is_ellipsis_args": false, "name": "get_options of PNABase", "ret_type": {".class": "Instance", "args": ["builtins.str"], "type_ref": "typing.Sequence"}, "variables": []}}}, "reset_averages": {".class": "SymbolTableNode", "kind": "Mdef", "node": {".class": "FuncDef", "arg_kinds": [0], "arg_names": ["self"], "flags": [], "fullname": "qcodes.instrument_drivers.Keysight.N52xx.PNABase.reset_averages", "name": "reset_averages", "type": null}}, "traces": {".class": "SymbolTableNode", "kind": "Mdef", "node": {".class": "Decorator", "func": {".class": "FuncDef", "arg_kinds": [0], "arg_names": ["self"], "flags": ["is_property", "is_decorated"], "fullname": "qcodes.instrument_drivers.Keysight.N52xx.PNABase.traces", "name": "traces", "type": {".class": "CallableType", "arg_kinds": [0], "arg_names": ["self"], "arg_types": ["qcodes.instrument_drivers.Keysight.N52xx.PNABase"], "bound_args": [], "def_extras": {"first_arg": "self"}, "fallback": "builtins.function", "implicit": false, "is_ellipsis_args": false, "name": "traces of PNABase", "ret_type": "qcodes.instrument.channel.ChannelList", "variables": []}}, "is_overload": false, "var": {".class": "Var", "flags": ["is_initialized_in_class", "is_property"], "fullname": null, "name": "traces", "type": {".class": "CallableType", "arg_kinds": [0], "arg_names": ["self"], "arg_types": ["qcodes.instrument_drivers.Keysight.N52xx.PNABase"], "bound_args": [], "def_extras": {"first_arg": "self"}, "fallback": "builtins.function", "implicit": false, "is_ellipsis_args": false, "name": "traces of PNABase", "ret_type": "qcodes.instrument.channel.ChannelList", "variables": []}}}}}, "tuple_type": null, "type_vars": [], "typeddict_type": null}}, "PNAPort": {".class": "SymbolTableNode", "kind": "Gdef", "node": {".class": "TypeInfo", "_promote": null, "abstract_attributes": [], "bases": ["qcodes.instrument.channel.InstrumentChannel"], "declared_metaclass": null, "defn": {".class": "ClassDef", "fullname": "qcodes.instrument_drivers.Keysight.N52xx.PNAPort", "name": "PNAPort", "type_vars": []}, "flags": [], "fullname": "qcodes.instrument_drivers.Keysight.N52xx.PNAPort", "metaclass_type": null, "metadata": {}, "module_name": "qcodes.instrument_drivers.Keysight.N52xx", "mro": ["qcodes.instrument_drivers.Keysight.N52xx.PNAPort", "qcodes.instrument.channel.InstrumentChannel", "qcodes.instrument.base.InstrumentBase", "qcodes.utils.metadata.Metadatable", "qcodes.utils.helpers.DelegateAttributes", "builtins.object"], "names": {".class": "SymbolTable", "__init__": {".class": "SymbolTableNode", "kind": "Mdef", "node": {".class": "FuncDef", "arg_kinds": [0, 0, 0, 0, 0, 0], "arg_names": ["self", "parent", "name", "port", "min_power", "max_power"], "flags": [], "fullname": "qcodes.instrument_drivers.Keysight.N52xx.PNAPort.__init__", "name": "__init__", "type": {".class": "CallableType", "arg_kinds": [0, 0, 0, 0, 0, 0], "arg_names": ["self", "parent", "name", "port", "min_power", "max_power"], "arg_types": ["qcodes.instrument_drivers.Keysight.N52xx.PNAPort", "qcodes.instrument_drivers.Keysight.N52xx.PNABase", "builtins.str", "builtins.int", {".class": "UnionType", "items": ["builtins.int", "builtins.float"]}, {".class": "UnionType", "items": ["builtins.int", "builtins.float"]}], "bound_args": [], "def_extras": {"first_arg": "self"}, "fallback": "builtins.function", "implicit": false, "is_ellipsis_args": false, "name": "__init__ of PNAPort", "ret_type": {".class": "NoneTyp"}, "variables": []}}}, "_set_power_limits": {".class": "SymbolTableNode", "kind": "Mdef", "node": {".class": "FuncDef", "arg_kinds": [0, 0, 0], "arg_names": ["self", "min_power", "max_power"], "flags": [], "fullname": "qcodes.instrument_drivers.Keysight.N52xx.PNAPort._set_power_limits", "name": "_set_power_limits", "type": {".class": "CallableType", "arg_kinds": [0, 0, 0], "arg_names": ["self", "min_power", "max_power"], "arg_types": ["qcodes.instrument_drivers.Keysight.N52xx.PNAPort", {".class": "UnionType", "items": ["builtins.int", "builtins.float"]}, {".class": "UnionType", "items": ["builtins.int", "builtins.float"]}], "bound_args": [], "def_extras": {"first_arg": "self"}, "fallback": "builtins.function", "implicit": false, "is_ellipsis_args": false, "name": "_set_power_limits of PNAPort", "ret_type": {".class": "NoneTyp"}, "variables": []}}}, "port": {".class": "SymbolTableNode", "implicit": true, "kind": "Mdef", "node": {".class": "Var", "flags": [], "fullname": "qcodes.instrument_drivers.Keysight.N52xx.PNAPort.port", "name": "port", "type": "builtins.int"}}}, "tuple_type": null, "type_vars": [], "typeddict_type": null}}, "PNASweep": {".class": "SymbolTableNode", "kind": "Gdef", "node": {".class": "TypeInfo", "_promote": null, "abstract_attributes": [], "bases": ["qcodes.instrument.parameter.ArrayParameter"], "declared_metaclass": null, "defn": {".class": "ClassDef", "fullname": "qcodes.instrument_drivers.Keysight.N52xx.PNASweep", "name": "PNASweep", "type_vars": []}, "flags": [], "fullname": "qcodes.instrument_drivers.Keysight.N52xx.PNASweep", "metaclass_type": null, "metadata": {}, "module_name": "qcodes.instrument_drivers.Keysight.N52xx", "mro": ["qcodes.instrument_drivers.Keysight.N52xx.PNASweep", "qcodes.instrument.parameter.ArrayParameter", "qcodes.instrument.parameter._BaseParameter", "qcodes.utils.metadata.Metadatable", "builtins.object"], "names": {".class": "SymbolTable", "__init__": {".class": "SymbolTableNode", "kind": "Mdef", "node": {".class": "FuncDef", "arg_kinds": [0, 0, 0, 4], "arg_names": ["self", "name", "instrument", "kwargs"], "flags": [], "fullname": "qcodes.instrument_drivers.Keysight.N52xx.PNASweep.__init__", "name": "__init__", "type": {".class": "CallableType", "arg_kinds": [0, 0, 0, 4], "arg_names": ["self", "name", "instrument", "kwargs"], "arg_types": ["qcodes.instrument_drivers.Keysight.N52xx.PNASweep", "builtins.str", "qcodes.instrument_drivers.Keysight.N52xx.PNABase", {".class": "AnyType", "missing_import_name": null, "source_any": null, "type_of_any": 2}], "bound_args": [], "def_extras": {"first_arg": "self"}, "fallback": "builtins.function", "implicit": false, "is_ellipsis_args": false, "name": "__init__ of PNASweep", "ret_type": {".class": "NoneTyp"}, "variables": []}}}, "setpoints": {".class": "SymbolTableNode", "kind": "Mdef", "node": {".class": "OverloadedFuncDef", "flags": ["is_property"], "fullname": "qcodes.instrument_drivers.Keysight.N52xx.PNASweep.setpoints", "impl": null, "items": [{".class": "Decorator", "func": {".class": "FuncDef", "arg_kinds": [0], "arg_names": ["self"], "flags": ["is_property", "is_overload", "is_decorated"], "fullname": "qcodes.instrument_drivers.Keysight.N52xx.PNASweep.setpoints", "name": "setpoints", "type": {".class": "CallableType", "arg_kinds": [0], "arg_names": ["self"], "arg_types": ["qcodes.instrument_drivers.Keysight.N52xx.PNASweep"], "bound_args": [], "def_extras": {"first_arg": "self"}, "fallback": "builtins.function", "implicit": false, "is_ellipsis_args": false, "name": "setpoints of PNASweep", "ret_type": {".class": "Instance", "args": [{".class": "AnyType", "missing_import_name": null, "source_any": null, "type_of_any": 4}], "type_ref": "typing.Sequence"}, "variables": []}}, "is_overload": true, "var": {".class": "Var", "flags": ["is_initialized_in_class", "is_property", "is_settable_property"], "fullname": null, "name": "setpoints", "type": {".class": "CallableType", "arg_kinds": [0], "arg_names": ["self"], "arg_types": ["qcodes.instrument_drivers.Keysight.N52xx.PNASweep"], "bound_args": [], "def_extras": {"first_arg": "self"}, "fallback": "builtins.function", "implicit": false, "is_ellipsis_args": false, "name": "setpoints of PNASweep", "ret_type": {".class": "Instance", "args": [{".class": "AnyType", "missing_import_name": null, "source_any": null, "type_of_any": 4}], "type_ref": "typing.Sequence"}, "variables": []}}}, {".class": "Decorator", "func": {".class": "FuncDef", "arg_kinds": [0, 0], "arg_names": ["self", "val"], "flags": ["is_decorated"], "fullname": "qcodes.instrument_drivers.Keysight.N52xx.PNASweep.setpoints", "name": "setpoints", "type": {".class": "CallableType", "arg_kinds": [0, 0], "arg_names": ["self", "val"], "arg_types": ["qcodes.instrument_drivers.Keysight.N52xx.PNASweep", {".class": "Instance", "args": ["builtins.int"], "type_ref": "typing.Sequence"}], "bound_args": [], "def_extras": {"first_arg": "self"}, "fallback": "builtins.function", "implicit": false, "is_ellipsis_args": false, "name": "setpoints of PNASweep", "ret_type": {".class": "NoneTyp"}, "variables": []}}, "is_overload": false, "var": {".class": "Var", "flags": [], "fullname": null, "name": "setpoints", "type": null}}], "type": {".class": "Overloaded", "items": [{".class": "CallableType", "arg_kinds": [0], "arg_names": ["self"], "arg_types": ["qcodes.instrument_drivers.Keysight.N52xx.PNASweep"], "bound_args": [], "def_extras": {"first_arg": "self"}, "fallback": "builtins.function", "implicit": false, "is_ellipsis_args": false, "name": "setpoints of PNASweep", "ret_type": {".class": "Instance", "args": [{".class": "AnyType", "missing_import_name": null, "source_any": null, "type_of_any": 4}], "type_ref": "typing.Sequence"}, "variables": []}]}}}, "shape": {".class": "SymbolTableNode", "kind": "Mdef", "node": {".class": "OverloadedFuncDef", "flags": ["is_property"], "fullname": "qcodes.instrument_drivers.Keysight.N52xx.PNASweep.shape", "impl": null, "items": [{".class": "Decorator", "func": {".class": "FuncDef", "arg_kinds": [0], "arg_names": ["self"], "flags": ["is_property", "is_overload", "is_decorated"], "fullname": "qcodes.instrument_drivers.Keysight.N52xx.PNASweep.shape", "name": "shape", "type": {".class": "CallableType", "arg_kinds": [0], "arg_names": ["self"], "arg_types": ["qcodes.instrument_drivers.Keysight.N52xx.PNASweep"], "bound_args": [], "def_extras": {"first_arg": "self"}, "fallback": "builtins.function", "implicit": false, "is_ellipsis_args": false, "name": "shape of PNASweep", "ret_type": {".class": "Instance", "args": ["builtins.int"], "type_ref": "typing.Sequence"}, "variables": []}}, "is_overload": true, "var": {".class": "Var", "flags": ["is_initialized_in_class", "is_property", "is_settable_property"], "fullname": null, "name": "shape", "type": {".class": "CallableType", "arg_kinds": [0], "arg_names": ["self"], "arg_types": ["qcodes.instrument_drivers.Keysight.N52xx.PNASweep"], "bound_args": [], "def_extras": {"first_arg": "self"}, "fallback": "builtins.function", "implicit": false, "is_ellipsis_args": false, "name": "shape of PNASweep", "ret_type": {".class": "Instance", "args": ["builtins.int"], "type_ref": "typing.Sequence"}, "variables": []}}}, {".class": "Decorator", "func": {".class": "FuncDef", "arg_kinds": [0, 0], "arg_names": ["self", "val"], "flags": ["is_decorated"], "fullname": "qcodes.instrument_drivers.Keysight.N52xx.PNASweep.shape", "name": "shape", "type": {".class": "CallableType", "arg_kinds": [0, 0], "arg_names": ["self", "val"], "arg_types": ["qcodes.instrument_drivers.Keysight.N52xx.PNASweep", {".class": "Instance", "args": ["builtins.int"], "type_ref": "typing.Sequence"}], "bound_args": [], "def_extras": {"first_arg": "self"}, "fallback": "builtins.function", "implicit": false, "is_ellipsis_args": false, "name": "shape of PNASweep", "ret_type": {".class": "NoneTyp"}, "variables": []}}, "is_overload": false, "var": {".class": "Var", "flags": [], "fullname": null, "name": "shape", "type": null}}], "type": {".class": "Overloaded", "items": [{".class": "CallableType", "arg_kinds": [0], "arg_names": ["self"], "arg_types": ["qcodes.instrument_drivers.Keysight.N52xx.PNASweep"], "bound_args": [], "def_extras": {"first_arg": "self"}, "fallback": "builtins.function", "implicit": false, "is_ellipsis_args": false, "name": "shape of PNASweep", "ret_type": {".class": "Instance", "args": ["builtins.int"], "type_ref": "typing.Sequence"}, "variables": []}]}}}}, "tuple_type": null, "type_vars": [], "typeddict_type": null}}, "PNATrace": {".class": "SymbolTableNode", "kind": "Gdef", "node": {".class": "TypeInfo", "_promote": null, "abstract_attributes": [], "bases": ["qcodes.instrument.channel.InstrumentChannel"], "declared_metaclass": null, "defn": {".class": "ClassDef", "fullname": "qcodes.instrument_drivers.Keysight.N52xx.PNATrace", "name": "PNATrace", "type_vars": []}, "flags": [], "fullname": "qcodes.instrument_drivers.Keysight.N52xx.PNATrace", "metaclass_type": null, "metadata": {}, "module_name": "qcodes.instrument_drivers.Keysight.N52xx", "mro": ["qcodes.instrument_drivers.Keysight.N52xx.PNATrace", "qcodes.instrument.channel.InstrumentChannel", "qcodes.instrument.base.InstrumentBase", "qcodes.utils.metadata.Metadatable", "qcodes.utils.helpers.DelegateAttributes", "builtins.object"], "names": {".class": "SymbolTable", "_Sparam": {".class": "SymbolTableNode", "kind": "Mdef", "node": {".class": "FuncDef", "arg_kinds": [0, 0], "arg_names": ["self", "paramspec"], "flags": [], "fullname": "qcodes.instrument_drivers.Keysight.N52xx.PNATrace._Sparam", "name": "_Sparam", "type": {".class": "CallableType", "arg_kinds": [0, 0], "arg_names": ["self", "paramspec"], "arg_types": ["qcodes.instrument_drivers.Keysight.N52xx.PNATrace", "builtins.str"], "bound_args": [], "def_extras": {"first_arg": "self"}, "fallback": "builtins.function", "implicit": false, "is_ellipsis_args": false, "name": "_Sparam of PNATrace", "ret_type": "builtins.str", "variables": []}}}, "__init__": {".class": "SymbolTableNode", "kind": "Mdef", "node": {".class": "FuncDef", "arg_kinds": [0, 0, 0, 0], "arg_names": ["self", "parent", "name", "trace"], "flags": [], "fullname": "qcodes.instrument_drivers.Keysight.N52xx.PNATrace.__init__", "name": "__init__", "type": {".class": "CallableType", "arg_kinds": [0, 0, 0, 0], "arg_names": ["self", "parent", "name", "trace"], "arg_types": ["qcodes.instrument_drivers.Keysight.N52xx.PNATrace", "qcodes.instrument_drivers.Keysight.N52xx.PNABase", "builtins.str", "builtins.int"], "bound_args": [], "def_extras": {"first_arg": "self"}, "fallback": "builtins.function", "implicit": false, "is_ellipsis_args": false, "name": "__init__ of PNATrace", "ret_type": {".class": "NoneTyp"}, "variables": []}}}, "_set_Sparam": {".class": "SymbolTableNode", "kind": "Mdef", "node": {".class": "FuncDef", "arg_kinds": [0, 0], "arg_names": ["self", "val"], "flags": [], "fullname": "qcodes.instrument_drivers.Keysight.N52xx.PNATrace._set_Sparam", "name": "_set_Sparam", "type": {".class": "CallableType", "arg_kinds": [0, 0], "arg_names": ["self", "val"], "arg_types": ["qcodes.instrument_drivers.Keysight.N52xx.PNATrace", "builtins.str"], "bound_args": [], "def_extras": {"first_arg": "self"}, "fallback": "builtins.function", "implicit": false, "is_ellipsis_args": false, "name": "_set_Sparam of PNATrace", "ret_type": {".class": "NoneTyp"}, "variables": []}}}, "ask": {".class": "SymbolTableNode", "kind": "Mdef", "node": {".class": "FuncDef", "arg_kinds": [0, 0], "arg_names": ["self", "cmd"], "flags": [], "fullname": "qcodes.instrument_drivers.Keysight.N52xx.PNATrace.ask", "name": "ask", "type": {".class": "CallableType", "arg_kinds": [0, 0], "arg_names": ["self", "cmd"], "arg_types": ["qcodes.instrument_drivers.Keysight.N52xx.PNATrace", "builtins.str"], "bound_args": [], "def_extras": {"first_arg": "self"}, "fallback": "builtins.function", "implicit": false, "is_ellipsis_args": false, "name": "ask of PNATrace", "ret_type": "builtins.str", "variables": []}}}, "parse_paramstring": {".class": "SymbolTableNode", "kind": "Mdef", "node": {".class": "Decorator", "func": {".class": "FuncDef", "arg_kinds": [0], "arg_names": ["paramspec"], "flags": ["is_static", "is_decorated"], "fullname": "qcodes.instrument_drivers.Keysight.N52xx.PNATrace.parse_paramstring", "name": "parse_paramstring", "type": {".class": "CallableType", "arg_kinds": [0], "arg_names": ["paramspec"], "arg_types": ["builtins.str"], "bound_args": [], "def_extras": {"first_arg": null}, "fallback": "builtins.function", "implicit": false, "is_ellipsis_args": false, "name": "parse_paramstring of PNATrace", "ret_type": {".class": "TupleType", "fallback": {".class": "Instance", "args": [{".class": "AnyType", "missing_import_name": null, "source_any": null, "type_of_any": 6}], "type_ref": "builtins.tuple"}, "implicit": false, "items": ["builtins.str", "builtins.str", "builtins.str"]}, "variables": []}}, "is_overload": false, "var": {".class": "Var", "flags": ["is_initialized_in_class", "is_staticmethod"], "fullname": null, "name": "parse_paramstring", "type": {".class": "CallableType", "arg_kinds": [0], "arg_names": ["paramspec"], "arg_types": ["builtins.str"], "bound_args": [], "def_extras": {"first_arg": null}, "fallback": "builtins.function", "implicit": false, "is_ellipsis_args": false, "name": "parse_paramstring of PNATrace", "ret_type": {".class": "TupleType", "fallback": {".class": "Instance", "args": [{".class": "AnyType", "missing_import_name": null, "source_any": null, "type_of_any": 6}], "type_ref": "builtins.tuple"}, "implicit": false, "items": ["builtins.str", "builtins.str", "builtins.str"]}, "variables": []}}}}, "run_sweep": {".class": "SymbolTableNode", "kind": "Mdef", "node": {".class": "FuncDef", "arg_kinds": [0], "arg_names": ["self"], "flags": [], "fullname": "qcodes.instrument_drivers.Keysight.N52xx.PNATrace.run_sweep", "name": "run_sweep", "type": {".class": "CallableType", "arg_kinds": [0], "arg_names": ["self"], "arg_types": ["qcodes.instrument_drivers.Keysight.N52xx.PNATrace"], "bound_args": [], "def_extras": {"first_arg": "self"}, "fallback": "builtins.function", "implicit": false, "is_ellipsis_args": false, "name": "run_sweep of PNATrace", "ret_type": "builtins.str", "variables": []}}}, "trace": {".class": "SymbolTableNode", "implicit": true, "kind": "Mdef", "node": {".class": "Var", "flags": [], "fullname": "qcodes.instrument_drivers.Keysight.N52xx.PNATrace.trace", "name": "trace", "type": "builtins.int"}}, "write": {".class": "SymbolTableNode", "kind": "Mdef", "node": {".class": "FuncDef", "arg_kinds": [0, 0], "arg_names": ["self", "cmd"], "flags": [], "fullname": "qcodes.instrument_drivers.Keysight.N52xx.PNATrace.write", "name": "write", "type": {".class": "CallableType", "arg_kinds": [0, 0], "arg_names": ["self", "cmd"], "arg_types": ["qcodes.instrument_drivers.Keysight.N52xx.PNATrace", "builtins.str"], "bound_args": [], "def_extras": {"first_arg": "self"}, "fallback": "builtins.function", "implicit": false, "is_ellipsis_args": false, "name": "write of PNATrace", "ret_type": {".class": "NoneTyp"}, "variables": []}}}}, "tuple_type": null, "type_vars": [], "typeddict_type": null}}, "PNAxBase": {".class": "SymbolTableNode", "kind": "Gdef", "node": {".class": "TypeInfo", "_promote": null, "abstract_attributes": [], "bases": ["qcodes.instrument_drivers.Keysight.N52xx.PNABase"], "declared_metaclass": null, "defn": {".class": "ClassDef", "fullname": "qcodes.instrument_drivers.Keysight.N52xx.PNAxBase", "name": "PNAxBase", "type_vars": []}, "flags": [], "fullname": "qcodes.instrument_drivers.Keysight.N52xx.PNAxBase", "metaclass_type": null, "metadata": {}, "module_name": "qcodes.instrument_drivers.Keysight.N52xx", "mro": ["qcodes.instrument_drivers.Keysight.N52xx.PNAxBase", "qcodes.instrument_drivers.Keysight.N52xx.PNABase", "qcodes.instrument.visa.VisaInstrument", "qcodes.instrument.base.Instrument", "qcodes.instrument.base.InstrumentBase", "qcodes.utils.metadata.Metadatable", "qcodes.utils.helpers.DelegateAttributes", "builtins.object"], "names": {".class": "SymbolTable", "__init__": {".class": "SymbolTableNode", "kind": "Mdef", "node": {".class": "FuncDef", "arg_kinds": [0, 0, 0, 0, 0, 0, 0, 0, 4], "arg_names": ["self", "name", "address", "min_freq", "max_freq", "min_power", "max_power", "nports", "kwargs"], "flags": [], "fullname": "qcodes.instrument_drivers.Keysight.N52xx.PNAxBase.__init__", "name": "__init__", "type": {".class": "CallableType", "arg_kinds": [0, 0, 0, 0, 0, 0, 0, 0, 4], "arg_names": ["self", "name", "address", "min_freq", "max_freq", "min_power", "max_power", "nports", "kwargs"], "arg_types": ["qcodes.instrument_drivers.Keysight.N52xx.PNAxBase", "builtins.str", "builtins.str", {".class": "UnionType", "items": ["builtins.int", "builtins.float"]}, {".class": "UnionType", "items": ["builtins.int", "builtins.float"]}, {".class": "UnionType", "items": ["builtins.int", "builtins.float"]}, {".class": "UnionType", "items": ["builtins.int", "builtins.float"]}, "builtins.int", {".class": "AnyType", "missing_import_name": null, "source_any": null, "type_of_any": 2}], "bound_args": [], "def_extras": {"first_arg": "self"}, "fallback": "builtins.function", "implicit": false, "is_ellipsis_args": false, "name": "__init__ of PNAxBase", "ret_type": {".class": "NoneTyp"}, "variables": []}}}, "_enable_fom": {".class": "SymbolTableNode", "kind": "Mdef", "node": {".class": "FuncDef", "arg_kinds": [0], "arg_names": ["self"], "flags": [], "fullname": "qcodes.instrument_drivers.Keysight.N52xx.PNAxBase._enable_fom", "name": "_enable_fom", "type": {".class": "CallableType", "arg_kinds": [0], "arg_names": ["self"], "arg_types": ["qcodes.instrument_drivers.Keysight.N52xx.PNAxBase"], "bound_args": [], "def_extras": {"first_arg": "self"}, "fallback": "builtins.function", "implicit": false, "is_ellipsis_args": false, "name": "_enable_fom of PNAxBase", "ret_type": {".class": "NoneTyp"}, "variables": []}}}}, "tuple_type": null, "type_vars": [], "typeddict_type": null}}, "Sequence": {".class": "SymbolTableNode", "cross_ref": "typing.Sequence", "kind": "Gdef"}, "Tuple": {".class": "SymbolTableNode", "cross_ref": "typing.Tuple", "kind": "Gdef"}, "Union": {".class": "SymbolTableNode", "cross_ref": "typing.Union", "kind": "Gdef"}, "VisaInstrument": {".class": "SymbolTableNode", "cross_ref": "qcodes.instrument.visa.VisaInstrument", "kind": "Gdef"}, "__doc__": {".class": "SymbolTableNode", "kind": "Gdef", "node": {".class": "Var", "flags": [], "fullname": "qcodes.instrument_drivers.Keysight.N52xx.__doc__", "name": "__doc__", "type": "builtins.str"}}, "__file__": {".class": "SymbolTableNode", "kind": "Gdef", "node": {".class": "Var", "flags": [], "fullname": "qcodes.instrument_drivers.Keysight.N52xx.__file__", "name": "__file__", "type": "builtins.str"}}, "__name__": {".class": "SymbolTableNode", "kind": "Gdef", "node": {".class": "Var", "flags": [], "fullname": "qcodes.instrument_drivers.Keysight.N52xx.__name__", "name": "__name__", "type": "builtins.str"}}, "__package__": {".class": "SymbolTableNode", "kind": "Gdef", "node": {".class": "Var", "flags": [], "fullname": "qcodes.instrument_drivers.Keysight.N52xx.__package__", "name": "__package__", "type": "builtins.str"}}, "np": {".class": "SymbolTableNode", "kind": "Gdef", "node": {".class": "Var", "flags": ["is_suppressed_import"], "fullname": "qcodes.instrument_drivers.Keysight.N52xx.np", "name": "np", "type": {".class": "AnyType", "missing_import_name": "qcodes.instrument_drivers.Keysight.N52xx.np", "source_any": null, "type_of_any": 3}}}, "re": {".class": "SymbolTableNode", "cross_ref": "re", "kind": "ModuleRef"}, "time": {".class": "SymbolTableNode", "cross_ref": "time", "kind": "ModuleRef"}}, "path": "qcodes/instrument_drivers/Keysight/N52xx.py"}
